toolbox/__init__.py
toolbox/stats.py
toolbox/utils.py
toolbox/version.py
tera_toolbox-0.1.50.dist-info/METADATA
tera_toolbox-0.1.50.dist-info/WHEEL
tera_toolbox-0.1.50.dist-info/entry_points.txt
tera_toolbox-0.1.50.dist-info/top_level.txt
tera_toolbox-0.1.50.dist-info/RECORD
